CHANGELOG.md
clone_repo/__init__.py
clone_repo/clone.py
clone_repo/main.py
clone_repo/parse_repo_url.py
clone_repo/py.typed
justfile
clone_repo-0.3.0.dist-info/LICENSE
clone_repo-0.3.0.dist-info/METADATA
clone_repo-0.3.0.dist-info/WHEEL
clone_repo-0.3.0.dist-info/entry_points.txt
clone_repo-0.3.0.dist-info/RECORD
