Metadata-Version: 2.1
Name: clone-repo
Version: 0.3.0
Summary: CLI tool to clone repos easily
Home-page: https://github.com/micktwomey/clone-repo
License: MIT
Author: Michael Twomey
Author-email: mick@twomeylee.name
Requires-Python: >=3.7,<4.0
Classifier: License :: OSI Approved :: MIT License
Classifier: Programming Language :: Python :: 3
Classifier: Programming Language :: Python :: 3.7
Classifier: Programming Language :: Python :: 3.8
Classifier: Programming Language :: Python :: 3.9
Classifier: Programming Language :: Python :: 3.10
Classifier: Programming Language :: Python :: 3.11
Requires-Dist: pyyaml (>=6.0.1)
Requires-Dist: rich (>=12.0,<13.0)
Requires-Dist: structlog (>=21.5,<22.0)
Requires-Dist: typer (>=0.4,<0.5)
Project-URL: Repository, https://github.com/micktwomey/clone-repo
